MANIFEST.in
README.md
setup.py
numertweak/__init__.py
numertweak/get_cols.py
numertweak/load_pandas.py
numertweak.egg-info/PKG-INFO
numertweak.egg-info/SOURCES.txt
numertweak.egg-info/dependency_links.txt
numertweak.egg-info/not-zip-safe
numertweak.egg-info/requires.txt
numertweak.egg-info/top_level.txt