Metadata-Version: 2.1
Name: numertweak
Version: 0.2.3
Summary: Some utility function for the numerai competition
Home-page: http://github.com/kmedian/numertweak
Author: Ulf Hamster
Author-email: 554c46@gmail.com
License: MIT
Platform: UNKNOWN
Requires-Python: >=3.6
